django_lispy_filter/__init__.py
django_lispy_filter/lib.py
django_lispy_filter/utils.py
django_lispy_filter-0.1.3.dist-info/LICENSE
django_lispy_filter-0.1.3.dist-info/WHEEL
django_lispy_filter-0.1.3.dist-info/METADATA
django_lispy_filter-0.1.3.dist-info/RECORD
